oc_checksumsq/__init__.py
oc_checksumsq/checksums_interface.py
oc_checksumsq-10.2.3.data/scripts/chkreg.py
oc_checksumsq-10.2.3.dist-info/LICENSE
oc_checksumsq-10.2.3.dist-info/METADATA
oc_checksumsq-10.2.3.dist-info/WHEEL
oc_checksumsq-10.2.3.dist-info/top_level.txt
oc_checksumsq-10.2.3.dist-info/RECORD
