Metadata-Version: 2.1
Name: oc-checksumsq
Version: 10.2.3
Summary: Client for CDT checksums queue
Home-page: UNKNOWN
License: UNKNOWN
Platform: UNKNOWN
Requires-Python: >=2.7,!=3.0.*,!=3.1.*,!=3.2.*,!=3.3.*,!=3.4.*,!=3.5.*
Requires-Dist: oc-cdt-queue2 (>=4.0.3)
Requires-Dist: requests
